apcloudy_pipeline/__init__.py
apcloudy_pipeline/client.py
apcloudy_pipeline/collector.py
apcloudy_pipeline/exceptions.py
apcloudy_pipeline/extensions.py
apcloudy_pipeline/log_handler.py
apcloudy_pipeline/middleware.py
apcloudy_pipeline/pipelines.py
apcloudy_pipeline/request_logger.py
apcloudy_pipeline/utils.py
apcloudy_pipeline-0.1.3.dist-info/licenses/LICENCE
apcloudy_pipeline-0.1.3.dist-info/METADATA
apcloudy_pipeline-0.1.3.dist-info/WHEEL
apcloudy_pipeline-0.1.3.dist-info/top_level.txt
apcloudy_pipeline-0.1.3.dist-info/RECORD
