Metadata-Version: 2.4
Name: apcloudy-pipeline
Version: 0.1.3
Summary: Scrapy pipeline & extensions for AP Cloudy (logs, stats, requests, items)
Home-page: https://github.com/fawadss1/apcloudy-pipeline
Author: Fawad
Author-email: fawadstar6@email.com
License: MIT
Classifier: Programming Language :: Python :: 3
Classifier: Framework :: Scrapy
Classifier: License :: OSI Approved :: MIT License
Classifier: Operating System :: OS Independent
Requires-Python: >=3.8
License-File: LICENCE
Requires-Dist: requests>=2.30.0
Dynamic: author
Dynamic: author-email
Dynamic: classifier
Dynamic: description
Dynamic: description-content-type
Dynamic: home-page
Dynamic: license
Dynamic: license-file
Dynamic: requires-dist
Dynamic: requires-python
Dynamic: summary
